jax_plugins/mps/__init__.py
jax_plugins/mps/lib/libpjrt_plugin_mps.dylib
jax_mps-0.9.4.dist-info/METADATA
jax_mps-0.9.4.dist-info/WHEEL
jax_mps-0.9.4.dist-info/entry_points.txt
jax_mps-0.9.4.dist-info/licenses/LICENSE
jax_mps-0.9.4.dist-info/RECORD
