Metadata-Version: 2.2
Name: jax-mps
Version: 0.9.4
Summary: JAX backend for Apple Metal Performance Shaders (MPS)
Keywords: jax,metal,mps,apple,gpu,machine-learning
License: Apache-2.0
Classifier: Development Status :: 3 - Alpha
Classifier: Intended Audience :: Developers
Classifier: Intended Audience :: Science/Research
Classifier: License :: OSI Approved :: Apache Software License
Classifier: Operating System :: MacOS
Classifier: Programming Language :: Python :: 3
Classifier: Topic :: Scientific/Engineering :: Artificial Intelligence
Project-URL: Homepage, https://github.com/tillahoffmann/jax-mps
Project-URL: Repository, https://github.com/tillahoffmann/jax-mps
Requires-Python: >=3.11
Requires-Dist: jax<0.10,>=0.9.0
Requires-Dist: jaxlib<0.10,>=0.9.0
